syntax_parser_prototype/__init__.py
syntax_parser_prototype/debug.py
syntax_parser_prototype/exceptions.py
syntax_parser_prototype/typing.py
syntax_parser_prototype/features/__init__.py
syntax_parser_prototype/features/indices.py
syntax_parser_prototype/features/readers.py
syntax_parser_prototype/features/tokenize.py
syntax_parser_prototype/main/__init__.py
syntax_parser_prototype/main/phrase.py
syntax_parser_prototype/main/streams.py
syntax_parser_prototype/main/tokens.py
syntax_parser_prototype-3.0.dist-info/LICENSE
syntax_parser_prototype-3.0.dist-info/METADATA
syntax_parser_prototype-3.0.dist-info/WHEEL
syntax_parser_prototype-3.0.dist-info/top_level.txt
syntax_parser_prototype-3.0.dist-info/RECORD
